<annotation>
	<folder>bedroom_resized</folder>
	<filename>00000103.jpg</filename>
	<path>D:\labelImg-master\demo\room_images\bedroom_resized\00000103.jpg</path>
	<source>
		<database>Unknown</database>
	</source>
	<size>
		<width>800</width>
		<height>534</height>
		<depth>3</depth>
	</size>
	<segmented>0</segmented>
	<object>
		<name>bed</name>
		<pose>Unspecified</pose>
		<truncated>0</truncated>
		<difficult>0</difficult>
		<bndbox>
			<xmin>16</xmin>
			<ymin>178</ymin>
			<xmax>528</xmax>
			<ymax>483</ymax>
		</bndbox>
	</object>
	<object>
		<name>lamp</name>
		<pose>Unspecified</pose>
		<truncated>0</truncated>
		<difficult>0</difficult>
		<bndbox>
			<xmin>306</xmin>
			<ymin>148</ymin>
			<xmax>351</xmax>
			<ymax>225</ymax>
		</bndbox>
	</object>
	<object>
		<name>chair</name>
		<pose>Unspecified</pose>
		<truncated>0</truncated>
		<difficult>0</difficult>
		<bndbox>
			<xmin>586</xmin>
			<ymin>206</ymin>
			<xmax>751</xmax>
			<ymax>400</ymax>
		</bndbox>
	</object>
</annotation>
